{
	"animations": [
		{
			"offsets": [
				71,
				-161
			],
			"loop": false,
			"fps": 24,
			"anim": "singLEFT",
			"indices": [],
			"name": "BLACK LEFT"
		},
		{
			"offsets": [
				176,
				-106
			],
			"loop": false,
			"fps": 24,
			"anim": "singRIGHT",
			"indices": [],
			"name": "BLACK RIGHT"
		},
		{
			"offsets": [
				-41,
				-152
			],
			"loop": false,
			"fps": 24,
			"anim": "singDOWN",
			"indices": [],
			"name": "BLACK DOWN"
		},
		{
			"offsets": [
				62,
				15
			],
			"loop": false,
			"fps": 24,
			"anim": "singUP",
			"indices": [],
			"name": "BLACK UP"
		},
		{
			"loop": true,
			"offsets": [
				102,
				-89
			],
			"anim": "idle",
			"fps": 24,
			"name": "BLACK IDLE",
			"indices": []
		},
		{
			"loop": false,
			"offsets": [
				130,
				872
			],
			"anim": "scream",
			"fps": 24,
			"name": "BLACK SCREAM",
			"indices": []
		}
	],
	"no_antialiasing": false,
	"image": "characters/story/black/danger",
	"position": [
		-410,
		20
	],
	"dance_every": 2,
	"gameover_intial_sound": null,
	"scalableOffsets": false,
	"gameover_confirm_sound": null,
	"healthicon": "black",
	"gameover_character": null,
	"vslice_sustains": false,
	"flip_x": false,
	"healthbar_colour": -12969137,
	"camera_position": [
		-500,
		-100
	],
	"gameover_loop_sound": null,
	"sing_duration": 4,
	"scale": 1.3,
	"_editor_isPlayer": false
}